wrapapi/__init__.py
wrapapi/logger.py
wrapapi/settings.py
wrapapi/test_suite.py
wrapapi/web.py
wrapapi/http/__init__.py
wrapapi/http/element.py
wrapapi/http/model.py
wrapapi/validations/__init__.py
wrapapi/validations/assertions.py
wrapapi/validations/conditions.py
wrapAPI-0.0.1.dist-info/LICENSE
wrapAPI-0.0.1.dist-info/METADATA
wrapAPI-0.0.1.dist-info/WHEEL
wrapAPI-0.0.1.dist-info/top_level.txt
wrapAPI-0.0.1.dist-info/RECORD
