Metadata-Version: 2.1
Name: wrapAPI
Version: 0.0.1
Summary: Requests wrapper for API testing
Home-page: UNKNOWN
Author: Denis Korytkin
Author-email: dkorytkin@gmail.com
License: UNKNOWN
Keywords: API,API testing,requests testing,requests wrapper
Platform: UNKNOWN
Classifier: Development Status :: 3 - Alpha
Classifier: License :: OSI Approved :: MIT License
Classifier: Programming Language :: Python :: 3
Classifier: Programming Language :: Python :: 3.6
Requires-Dist: requests
Provides-Extra: test
Requires-Dist: pytest ; extra == 'test'
